AUTHORS
COPYING
setup.cfg
setup.py
/Users/kylealanhale/Documents/Dev/Python/quicli/build/lib/quicli.egg-info/SOURCES.txt
quicli/__init__.py
quicli/decorators.py
quicli/guts.py
quicli/progress.py
tests/__init__.py
tests/test_main.py
tests/test_progress.py
tests/scenarios/__init__.py
tests/scenarios/badargument1.py
tests/scenarios/badargument2.py
tests/scenarios/direct.py
tests/scenarios/filechecks.py
tests/scenarios/modify.py
tests/scenarios/optional.py
tests/scenarios/restart.py
tests/scenarios/runlater.py
tests/scenarios/simple.py
tests/scenarios/subparser.py
tests/scenarios/validate.py