Metadata-Version: 1.0
Name: quicli
Version: 1.1.0
Summary: quicli: write command line interfaces quickly
Home-page: http://dev.kylealanhale.com/wiki/projects/quicli
Author: Kyle Alan Hale
Author-email: kylealanhale@gmail.com
License: BSD
Keywords: command line cli
Platform: UNKNOWN
Classifier: Programming Language :: Python
Classifier: Programming Language :: Python :: 3
Classifier: Development Status :: 4 - Beta
Classifier: Intended Audience :: Developers
Classifier: Topic :: Software Development
Classifier: Environment :: Console
